recfarm-0.2.1.dist-info/METADATA
recfarm-0.2.1.dist-info/WHEEL
recfarm/__init__.py
recfarm/recfarm.abi3.so
recfarm-0.2.1.dist-info/RECORD
